{
   "datetime": 1622383275,
   "donate_url": "https://www.paypal.com/paypalme/JonaSchnedi",
   "error": false,
   "filehash": "419c2bc65acde1904360acdcf864232d",
   "filename": "Derp_2.2-lmi-11-30052021-1602.zip",
   "forum_url": "https://forum.xda-developers.com/t/rom-lmi-11-derp-2-2-30-05-21.4220171/",
   "id": "b170cd69ec1b636ec261e870c1a9b3d92a2fea26b00deaeb4307950e7041232a",
   "maintainer": "Schnedi",
   "maintainer_url": "https://forum.xda-developers.com/m/schnedi.4315759/",
   "news_url": "https://t.me/derpf2pro",
   "size": 1333662594,
   "telegram_username": "RealSchnedi",
   "url": "https://sourceforge.net/projects/lmi/files/Derp_2.2-lmi-11-30052021-1602.zip/download",
   "version": "2.2",
   "website_url": "https://t.me/derpf2pro"
}
